[
  {
    "code": "87-1",
    "title": "운전경력증명서 발급 신청서",
    "category": "우즈벡어(o'zbek)",
    "description": "Haydovchilik tajribasi guvohnomasini berish uchun ariza",
    "pdf": "https://drive.google.com/uc?id=1X9t4ropHvl3nx2bMGyVpYJJ93H6osfeX",
    "hwp": "nan",
    "doc": "nan",
    "xls": "nan"
  },
  {
    "code": "87-2",
    "title": "운전면허 정기(수시)적성검사 제1종 대형,특수,소형 신청서",
    "category": "우즈벡어(o'zbek)",
    "description": "Haydovchilik guvohnomasining muntazam (davriy) 1-turdagi qobiliyat imtihonining katta, maxsus, kichik ariza shakli",
    "pdf": "https://drive.google.com/uc?id=1v4ykwrdrtQJwlnilrD1BvAqnBYEjSG_M",
    "hwp": "nan",
    "doc": "nan",
    "xls": "nan"
  },
  {
    "code": "87-3",
    "title": "운전면허 정기(수시)적성검사 제1종 보통, 제2종 신청서",
    "category": "우즈벡어(o'zbek)",
    "description": "Haydovchilik guvohnomasining muntazam (davriy) 1-turdagi qobiliyat imtihonining oddiy, 2-toifa ariza shakli",
    "pdf": "https://drive.google.com/uc?id=10wniYmr76M9ptA5qhL_TpeMJ7qlBNZdZ",
    "hwp": "nan",
    "doc": "nan",
    "xls": "nan"
  },
  {
    "code": "87-4",
    "title": "자동차운전면허증 갱신, 자동차운전면허증 재발급, 영문ㆍ국제ㆍ모바일운전면허증 발급, 운전면허증갱신발급(적성검사)연기) 신청서",
    "category": "우즈벡어(o'zbek)",
    "description": "Haydovchilik guvohnomasini yangilash uchun ariza, haydovchilik guvohnomasini qayta rasmiylashtirish, ingliz/xalqaro/mobil haydovchilik guvohnomasini berish, haydovchilik guvohnomasini uzaytirish muddatini kechiktirish (qobiliyat imtihoni)",
    "pdf": "https://drive.google.com/uc?id=1uPegkMaCqeX9YNRCynyAyrYuBYAu64DM",
    "hwp": "nan",
    "doc": "nan",
    "xls": "nan"
  },
  {
    "code": "87-5",
    "title": "정보공개 청구서",
    "category": "우즈벡어(o'zbek)",
    "description": "Axborotni oshkor qilish da'vosi",
    "pdf": "https://drive.google.com/uc?id=1kY_YesThKZtchpQnHvlfc9V2jvGMgpB4",
    "hwp": "nan",
    "doc": "nan",
    "xls": "nan"
  }
]
